{
  "full_name": "Earth Warden",
  "frame_image": "/assets/ui/hero-frame.webp",
  "char_bg_pos": {
    "x": 17,
    "y": 206
  },
  "char_fg_pos": {
    "x": 17,
    "y": 206
  },
  "char_bg_scale": 197,
  "char_fg_scale": 197,
  "name_pos": {
    "x": 0,
    "y": 91
  },
  "name_scale": 57,
  "text_shadow_color": "rgba(0, 0, 0, 0.5)",
  "tint": "#fff56b",
  "hp_bar_pos": {
    "x": 0,
    "y": 151
  },
  "hp_bar_scale": 250,
  "hp_bar_current": 100,
  "hp_bar_max": 100,
  "hp_bar_hue": 85,
  "hp_bar_font_size": 31,
  "lore": "An avatar of the mountain. Unshakeable and eternal, yet they cannot grasp the elusive nature of the wind, which erodes them over time.",
  "stats": {
    "max_hp": 3600,
    "attack": 120,
    "defense": 170,
    "element_affinity": {
      "earth": 40,
      "fire": 0,
      "ice": 0,
      "light": 0,
      "shadow": 0,
      "wind": -30
    }
  },
  "audio": null,
  "pose": null
}