{
  "full_name": "Holy",
  "frame_image": "/assets/ui/action-frame.webp",
  "char_bg_pos": {
    "x": 10,
    "y": 1
  },
  "char_bg_scale": 138,
  "name_pos": {
    "x": 0,
    "y": 500
  },
  "name_scale": 122,
  "text_shadow_color": "rgba(0, 0, 0, 0.5)",
  "tint": "#dfb335",
  "description": "Call down sacred power to smite a single enemy with radiant judgment.",
  "cost": 3,
  "element": [
    "light"
  ],
  "target_rule": "enemy_single",
  "visible_layers": {
    "card": true,
    "char-bg": true,
    "name": true
  },
  "targeting": {
    "side": "enemy",
    "scope": "single",
    "selection": "manual",
    "allow_self": false,
    "allow_dead": false
  },
  "text_shadow_size": 3
}
